{"sku":"PMF_GO","product_name":"Gold/Orange Fly","long_description":"The dressed tail adds extra bulk and color attraction.   The all silver and all gold with barrel shaped bodies are truly effective on many species of fish.","category":"Deluxe Fly","thumb_url":"http://panthermartin.com/img/Small/PMF_GO.jpg","image_url":"http://panthermartin.com/img/Medium/PMF_GO.jpg","buy_link":"http://www.avantlink.com/click.php?p=154933&pw=55475&pt=3&pri=1111&tt=df","retail_price":"4.49","sale_price":"4.49","product_page_view_tracking":"<img src=\"http://www.avantlink.com/dfpv.php?p=154933&amp;pri=1111\" width=\"0\" height=\"0\" style=\"border: none !important; margin: 0px !important;\" alt=\"\" />","product_content_widget":"<script type=\"text/javascript\" src=\"http://www.avantlink.com/apcw.php?mode=5&amp;pw=55475&amp;df=1197&amp;sku=PMF_GO&amp;link=&amp;tabs=-Details\"></script>","google_categorization":"Sporting Goods > Outdoor Recreation > Fishing > Fishing Lures","variants":{"PMF_1_GO":{"sku":"PMF_1_GO","size":"1/32 oz.","retail_price":"4.49"},"PMF_2_GO":{"sku":"PMF_2_GO","size":"1/16 oz.","retail_price":"4.49"},"PMF_4_GO":{"sku":"PMF_4_GO","size":"1/8 oz.","retail_price":"4.49"},"PMF_6_GO":{"sku":"PMF_6_GO","size":"1/4 oz.","retail_price":"4.49"}}}
