{"sku":"PMGRSK","product_name":"Red Speckled with gold blade","long_description":"Our Classic patterns are time tested lures that are deadly on Stream and Lake Trout.","category":"Classic Patterns","thumb_url":"http://panthermartin.com/img/Small/PMGRSK.jpg","image_url":"http://panthermartin.com/img/Medium/PMGRSK.jpg","buy_link":"http://www.avantlink.com/click.php?p=154933&pw=55475&pt=3&pri=999&tt=df","retail_price":"3.99","sale_price":"3.99","product_page_view_tracking":"<img src=\"http://www.avantlink.com/dfpv.php?p=154933&amp;pri=999\" width=\"0\" height=\"0\" style=\"border: none !important; margin: 0px !important;\" alt=\"\" />","product_content_widget":"<script type=\"text/javascript\" src=\"http://www.avantlink.com/apcw.php?mode=5&amp;pw=55475&amp;df=1197&amp;sku=PMGRSK&amp;link=&amp;tabs=-Details\"></script>","google_categorization":"Sporting Goods > Outdoor Recreation > Fishing > Fishing Lures","variants":{"PMGRSK_2_":{"sku":"PMGRSK_2_","size":"1/16 oz.","retail_price":"3.99"},"PMGRSK_4_":{"sku":"PMGRSK_4_","size":"1/8 oz.","retail_price":"3.99"},"PMGRSK_6_":{"sku":"PMGRSK_6_","size":"1/4 oz.","retail_price":"3.99"}}}
