{"bought":{"pmbbmfp":{"title":"Flaming Pink Stainless Steel Salmon","sale_price":"4.99","url":"/salmon-steelhead/pmbbmfp.html"},"pmbbmfo":{"title":"Flaming Orange Stainless Steel Salmon","sale_price":"4.99","url":"/salmon-steelhead/pmbbmfo.html"},"pmbbmfc":{"title":"Fl Chartreuse Stainless Steel Salmon","sale_price":"4.99","url":"/salmon-steelhead/pmbbmfc.html"},"pmmrg":{"title":"Gold Metallic Red Body","sale_price":"4.49","url":"/salmon-steelhead/pmmrg.html"}},"viewed":{"froghgr":{"title":"Green Holographic Superior Frog","sale_price":"4.29","url":"/holographic-superior-frog/froghgr.html"},"pmmbf":{"title":"Blue Metal Flake","sale_price":"4.49","url":"/classic-patterns-dressed/pmmbf.html"},"pmrsalg":{"title":"Gold Salamander","sale_price":"3.99","url":"/classic-patterns/pmrsalg.html"},"pmhdpbh":{"title":"Purple/Blue Hol Holographic Deluxe","sale_price":"4.49","url":"/holographic-deluxe/pmhdpbh.html"}},"together":{"pmmbs":{"title":"Silver Metallic Light Blue body","sale_price":"4.49","url":"/salmon-steelhead/pmmbs.html"}}}
