{"bought":{"pmbbmfo":{"title":"Flaming Orange Stainless Steel Salmon","sale_price":"4.99","url":"/salmon-steelhead/pmbbmfo.html"},"pmmbs":{"title":"Silver Metallic Light Blue body","sale_price":"4.49","url":"/salmon-steelhead/pmmbs.html"},"pmbbmfp":{"title":"Flaming Pink Stainless Steel Salmon","sale_price":"4.99","url":"/salmon-steelhead/pmbbmfp.html"},"pmbbmmb":{"title":"Metallic Blue Stainless Steel Salmon","sale_price":"4.99","url":"/salmon-steelhead/pmbbmmb.html"}},"viewed":{"pmhdggh":{"title":"Gold/Green Holo Holographic Deluxe","sale_price":"4.49","url":"/holographic-deluxe/pmhdggh.html"},"pmrshs":{"title":"Silver Single Hook","sale_price":"3.99","url":"/classic-single-hooks/pmrshs.html"},"pmrsb":{"title":"Silver/Black Regular","sale_price":"3.99","url":"/classic-regular/pmrsb.html"},"pmssltp":{"title":"Pink Stainless Steel Lightning","sale_price":"3.99","url":"/painted-stainless-steel/pmssltp.html"}},"together":{"pmbbmfc":{"title":"Fl Chartreuse Stainless Steel Salmon","sale_price":"4.99","url":"/salmon-steelhead/pmbbmfc.html"}}}
