{"bought":{"pmfsy":{"title":"Silver/Yellow Fly","sale_price":"4.49","url":"/deluxe-fly/pmfsy.html"},"pmfcy":{"title":"Copper/Yellow Fly","sale_price":"4.49","url":"/deluxe-fly/pmfcy.html"},"pmfgo":{"title":"Gold/Orange Fly","sale_price":"4.49","url":"/deluxe-fly/pmfgo.html"},"pmfso":{"title":"Silver/Orange Fly","sale_price":"4.49","url":"/deluxe-fly/pmfso.html"}},"viewed":{"pmmkwpb":{"title":"White/Purp/Blue Muskie Marabuck","sale_price":"19.99","url":"/muskie-marabuck/pmmkwpb.html"},"pmcap":{"title":"Panther Martin Cap","sale_price":"13.69","url":"/apparel/pmcap.html"},"pmsstuvmrw":{"title":"Red/White Salmon & Steelhead Marabou","sale_price":"5.29","url":"/fishseeuv-salmon-steelhead-marabou/pmsstuvmrw.html"},"pmhbbh":{"title":"Blue/Black Holo Holographic","sale_price":"4.19","url":"/holographic-regular/pmhbbh.html"}},"together":{"pmfco":{"title":"Copper/Orange Fly","sale_price":"4.49","url":"/deluxe-fly/pmfco.html"}}}
