{"bought":{},"viewed":{"vv12strh":{"title":"Spotted Trout Vivif","sale_price":"2.14","url":"/vivif-swimbait-packages/vv12strh.html"},"umb13ssh":{"title":"SuperSilverHolo Umbrella Rig (5 Lures)","sale_price":"34.99","url":"/umbrella-rig-5-lures/umb13ssh.html"},"pmcbcbk":{"title":"Copper/Black Classic Copper","sale_price":"3.99","url":"/classic-regular/pmcbcbk.html"},"pmmbf":{"title":"Blue Metal Flake","sale_price":"4.49","url":"/classic-patterns-dressed/pmmbf.html"}},"together":{"pmhfftor":{"title":"FTH/Orange Red Holographic Fly","sale_price":"4.49","url":"/holographic-fly/pmhfftor.html"}}}
