{"bought":{"pmhsgh":{"title":"Silver/GoldHolo Holographic","sale_price":"4.19","url":"/holographic-regular/pmhsgh.html"},"pmhch":{"title":"Chartreuse Holographic","sale_price":"4.19","url":"/holographic-regular/pmhch.html"},"pmhbbh":{"title":"Blue/Black Holo Holographic","sale_price":"4.19","url":"/holographic-regular/pmhbbh.html"},"pmhsbh":{"title":"Silver/Blue Holographic","sale_price":"4.19","url":"/holographic-regular/pmhsbh.html"}},"viewed":{"vv16bkr":{"title":"Bunker Vivif Double Trouble","sale_price":"10.49","url":"/9in-vivif-double-trouble/vv16bkr.html"},"pmcbcy":{"title":"Copper/Yellow Classic Copper","sale_price":"3.99","url":"/classic-regular/pmcbcy.html"},"pmspfby":{"title":"Black Yellow Spotted Fly","sale_price":"4.49","url":"/classic-patterns-dressed/pmspfby.html"},"wwni":{"title":"Nickel WeedWing","sale_price":"4.29","url":"/weedwing/wwni.html"}},"together":{"pmhrth":{"title":"Rainbow/Trout Holographic","sale_price":"4.19","url":"/holographic-regular/pmhrth.html"}}}
